almirah/__init__.py
almirah/core/__init__.py
almirah/core/base.py
almirah/core/db.py
almirah/core/uniquify.py
almirah/database.py
almirah/dataset.py
almirah/indexer.py
almirah/layout.py
almirah/specification.py
almirah/utils/__init__.py
almirah/utils/convert.py
almirah/utils/df.py
almirah/utils/gen.py
almirah/utils/lib.py
almirah/utils/logging.py
almirah/utils/sqlalchemy.py
almirah-0.5.1.dist-info/LICENSE
almirah-0.5.1.dist-info/METADATA
almirah-0.5.1.dist-info/WHEEL
almirah-0.5.1.dist-info/RECORD
