Metadata-Version: 2.1
Name: almirah
Version: 0.5.1
Summary: a dataset management tool
License: MIT
Author: girish
Author-email: girishmm@ncbs.res.in
Requires-Python: >=3.9,<4.0
Classifier: License :: OSI Approved :: MIT License
Classifier: Programming Language :: Python :: 3
Classifier: Programming Language :: Python :: 3.9
Classifier: Programming Language :: Python :: 3.10
Classifier: Programming Language :: Python :: 3.11
Classifier: Programming Language :: Python :: 3.12
Requires-Dist: datalad (>=0.19.3,<0.20.0)
Requires-Dist: pandas (>=2.0,<3.0)
Requires-Dist: pyyaml (>=6.0.0,<7.0.0)
Requires-Dist: requests (>=2.31.0,<3.0.0)
Requires-Dist: sqlalchemy (>=2.0.20,<3.0.0)
Requires-Dist: sqlalchemy-json (>=0.6.0,<0.7.0)
